LICENSE.md
MANIFEST.in
README.md
icon.png
setup.py
AirStrip.egg-info/PKG-INFO
AirStrip.egg-info/SOURCES.txt
AirStrip.egg-info/dependency_links.txt
AirStrip.egg-info/requires.txt
AirStrip.egg-info/top_level.txt
airstrip/.DS_Store
airstrip/__init__.py
airstrip/__init__.pyc
airstrip/air.py
airstrip/airbuild.py
airstrip/airconfig.py
airstrip/airfile.py
airstrip/airlicenses.py
airstrip/airrc.py
airstrip/githelper.py
airstrip/github.py
airstrip/global.json
airstrip/pukefile.py
airstrip/seeder.py
airstrip/airs/.DS_Store
airstrip/airs/backbone.json
airstrip/airs/bootstrap.json
airstrip/airs/console.json
airstrip/airs/ember.json
airstrip/airs/es5.json
airstrip/airs/h5bp.json
airstrip/airs/handlebars.json
airstrip/airs/headjs.json
airstrip/airs/hoverintent.json
airstrip/airs/i18n.json
airstrip/airs/ie7.json
airstrip/airs/jasmine.json
airstrip/airs/jquery.json
airstrip/airs/js.core.json
airstrip/airs/jsboot.json
airstrip/airs/json3.json
airstrip/airs/labjs.json
airstrip/airs/moment.json
airstrip/airs/mousetrap.json
airstrip/airs/normalize.json
airstrip/airs/phoneapp.json
airstrip/airs/pie.json
airstrip/airs/raphael.json
airstrip/airs/requirejs.json
airstrip/airs/spitfire.json
airstrip/airs/stacktrace.json
airstrip/airs/xmlhttprequest.json
airstrip/airs/yepnopejs.json
airstrip/airs/yui3.json
airstrip/airs/zepto.json
airstrip/bin/airstrip
airstrip/boilerplates/.DS_Store
airstrip/boilerplates/.gitignore
airstrip/boilerplates/.jshintrc
airstrip/boilerplates/.pukeignore
airstrip/boilerplates/LICENSE.md
airstrip/boilerplates/README.md
airstrip/boilerplates/TODO
airstrip/boilerplates/helpers.py
airstrip/boilerplates/icon.png
airstrip/boilerplates/package.json
airstrip/boilerplates/project.sublime-project
airstrip/boilerplates/pukefile.py
airstrip/boilerplates/src/.DS_Store
airstrip/boilerplates/src/index.html
airstrip/boilerplates/src/miniboot.css
airstrip/boilerplates/src/miniboot.ico
airstrip/boilerplates/src/miniboot.js
airstrip/boilerplates/src/assets/images/logo.png
airstrip/licenses/agpl
airstrip/licenses/mit