Metadata-Version: 1.0
Name: AirStrip
Version: 2.0.2
Summary: Third-party js dependencies manager
Home-page: http://airstrip.jsboot.com/
Author: WebItUp
Author-email: tech@webitup.fr
License: Copyright (C) 2013 WebItUp. All rights reserved.
